django_discover_runner-0.4.dist-info/METADATA
django_discover_runner-0.4.dist-info/RECORD
django_discover_runner-0.4.dist-info/top_level.txt
django_discover_runner-0.4.dist-info/WHEEL
usr/local/lib/python2.7/site-packages/discover_runner/__init__.py
usr/local/lib/python2.7/site-packages/discover_runner/runner.py
usr/local/lib/python2.7/site-packages/discover_runner/settings.py
usr/local/lib/python2.7/site-packages/discover_runner/management/__init__.py
usr/local/lib/python2.7/site-packages/discover_runner/management/commands/__init__.py
usr/local/lib/python2.7/site-packages/discover_runner/management/commands/test.py
