Metadata-Version: 1.1
Name: django-discover-runner
Version: 0.4
Summary: A Django test runner based on unittest2's test discovery.
Home-page: http://github.com/jezdez/django-discover-runner
Author: Carl Meyer, Jannis Leidel
Author-email: carl@dirtcircle.com, jannis@leidel.info
License: BSD
Platform: UNKNOWN
Classifier: Development Status :: 4 - Beta
Classifier: Environment :: Web Environment
Classifier: Framework :: Django
Classifier: Intended Audience :: Developers
Classifier: License :: OSI Approved :: BSD License
Classifier: Operating System :: OS Independent
Classifier: Programming Language :: Python
Classifier: Programming Language :: Python :: 2.5
Classifier: Programming Language :: Python :: 2.6
Classifier: Programming Language :: Python :: 2.7
Classifier: Programming Language :: Python :: 3.2
Classifier: Programming Language :: Python :: 3.3
